Metadata-Version: 1.2
Name: yandex-cloud-tools
Version: 1.0.0
Summary: Tools for YandexCloud
Home-page: https://github.com/maximshumilo/tools
Author: Shumilo Maksim
Author-email: shumilo.mk@gmail.com
License: UNKNOWN
Platform: UNKNOWN
Classifier: Development Status :: 3 - Alpha
Classifier: Programming Language :: Python :: 3.8
Classifier: Intended Audience :: Developers
Classifier: Topic :: Software Development
Classifier: License :: OSI Approved :: MIT License
Classifier: Operating System :: OS Independent
Requires-Python: >=3.8
